LICENSE
MANIFEST.in
README.rst
setup.py
js/__init__.py
js.unicode_eastasianwidth.egg-info/PKG-INFO
js.unicode_eastasianwidth.egg-info/SOURCES.txt
js.unicode_eastasianwidth.egg-info/dependency_links.txt
js.unicode_eastasianwidth.egg-info/entry_points.txt
js.unicode_eastasianwidth.egg-info/namespace_packages.txt
js.unicode_eastasianwidth.egg-info/not-zip-safe
js.unicode_eastasianwidth.egg-info/requires.txt
js.unicode_eastasianwidth.egg-info/top_level.txt
js/unicode_eastasianwidth/__init__.py
js/unicode_eastasianwidth/test_unicode_eastasianwidth.txt
js/unicode_eastasianwidth/resources/angular-unicode_eastasianwidth.js
js/unicode_eastasianwidth/resources/angular-unicode_eastasianwidth.min.js
js/unicode_eastasianwidth/resources/unicode_eastasianwidth.js
js/unicode_eastasianwidth/resources/unicode_eastasianwidth.min.js