Metadata-Version: 1.0
Name: js.unicode-eastasianwidth
Version: 0.2.1-1
Summary: Fanstatic packaging of Counting the unicode characters based Unicode East Asian Width database for JavaScript. It includes some tools for dealing with characters.
Home-page: UNKNOWN
Author: UNKNOWN
Author-email: UNKNOWN
License: MIT
Platform: UNKNOWN
Classifier: Programming Language :: Python :: 2.6
Classifier: Programming Language :: Python :: 2.7
Classifier: Programming Language :: Python :: 3.2
Classifier: Programming Language :: Python :: Implementation :: PyPy
